{
  "cuentas": {
    "ACTIVO": {
      "Activos Circulantes": {
        "Disponible": [
          "101-108",
          "109-119"
        ],
        "Realizable": [
          "120-139",
          "140-151",
          "152-169",
          "170-179"
        ],
        "Otros Activos Circulantes": [
          "180-189",
          "190-199"
        ]
      },
      "Activos Fijos Tangibles": {
        "Total": [
          "200-249"
        ]
      },
      "Inversiones": {
        "Total": [
          "250-289"
        ]
      },
      "Otros Activos": {
        "Total": [
          "290-299"
        ]
      }
    },
    "PASIVO": {
      "Pasivos Circulantes": {
        "Total": [
          "400-419",
          "420-429",
          "430-449",
          "450-459",
          "460-469",
          "470-499"
        ]
      },
      "Pasivos a Largo Plazo": {
        "Total": [
          "500-519",
          "520-529",
          "530-539",
          "540-549"
        ]
      },
      "Otros Pasivos": {
        "Total": [
          "550-599"
        ]
      }
    },
    "CAPITAL": {
      "Capital": {
        "Total": [
          "600-699"
        ]
      },
      "Gastos": {
        "Total": [
          "800-899"
        ]
      },
      "Ingresos": {
        "Total": [
          "900-999"
          
        ]
      }
    }
  }
}