{
  "id": "ERROR_AUDIT_1__clasificación_profesional_de_hallazgos",
  "content": "## 1. Clasificación Profesional de Hallazgos\n\n| Archivo | Tipo | Severidad | Descripción | Impacto Negocio | Flujo |\n| :--- | :--- | :--- | :--- | :--- | :--- |\n| `src/app/login/page.tsx` | TS | 🔴 Crítico | Propiedad `active_store_id` faltante en objeto User. | Impide el login correcto y asociación de tienda. | Auth / POS |\n| `src/components/views/TerminalView.tsx` | TS | 🔴 Crítico | Referencia a `loading` en `AuthStore` (no existe en el store). | Rompe la vista principal del terminal. | Auth / POS |\n| `src/components/views/TerminalView.tsx` | TS | 🔴 Crítico | Decenas de `Cannot find name` (Variables/Funciones de estado desaparecidas). | El terminal está funcionalmente roto (POS, Pagos, Filtros). | POS / Terminal |\n| `src/components/views/TerminalView.tsx` | TS | 🔴 Crítico | Incompatibilidad de tipos en manejadores de carrito (`CartItem` vs `Product`). | Errores en la lógica de agregado al carrito. | POS |\n| `src/components/cost-sheets/CostSheetView.tsx` | TS | 🔴 Crítico | Propiedad `annexes` no existe en el tipo de valores calculados. | Rompe el motor de cálculo de fichas de costo. | Costos |\n| `src/components/ProductReceptionView.tsx` | TS | 🔴 Crítico | Objeto `Product` incompleto (faltan 9+ propiedades requeridas). | Falla en la recepción de mercancía y actualización de stock. | Inventario |\n| `src/lib/db.ts` | TS | 🔴 Crítico | `PrismaClient` no encontrado en `@prisma/client`. | Riesgo de fallo total en capa de persistencia (si se usa). | Base de Datos |\n| `src/components/CatalogView.tsx` | TS | 🟠 Medio | Propiedad `className` no permitida en tipo `Action`. | Posible fallo en renderizado de menús de acción. | POS / Catálogo |\n| `src/components/InventoryView.tsx` | TS | 🟠 Medio | Propiedad `className` no permitida en tipo `Action`. | Posible fallo en renderizado de menús de inventario. | Inventario |\n| `src/components/ui/ProductImage.tsx` | TS | 🟠 Medio | `null` no asignable a `string \\| StaticImport`. | Errores visuales/runtime al cargar imágenes de productos. | UI / Catálogo |\n| `src/components/theme-provider.tsx` | TS | 🟠 Medio | Módulo `next-themes/dist/types` no encontrado. | Inestabilidad en el sistema de temas. | UI |\n| `src/components/views/terminal/POSView.tsx` | TS | 🟠 Medio | `null` no asignable a tipos de entrada (string/number). | Bugs menores en inputs del POS. | POS |\n| `src/components/CostProLogo.tsx` | TS | 🟢 Bajo | Mismatch en tipos de variantes de framer-motion (ease). | Animación del logo podría no comportarse como se espera. | UI |\n| `src/components/ui/DataDecryption.tsx` | TS | 🟢 Bajo | Uso de propiedad `yoyo` obsoleta en transiciones. | Advertencia de deprecación en consola. | UI |\n| `examples/websocket/*` | TS | 🟢 Bajo | Dependencias faltantes (`socket.io`). | Ejemplos no compilables. | Otros |\n| `skills/frontend-design/*` | TS | 🟢 Bajo | Errores de tipos en archivos de entrenamiento/ejemplo. | Ruido en el build. | Otros |\n\n",
  "metadata": {
    "source": "knowledge/docs/reference/ERROR_AUDIT.md",
    "header": "1. Clasificación Profesional de Hallazgos"
  }
}