{
  "id": "AUDIT_LOG_5__registro_de_madurez_del_sistema",
  "content": "### 5. REGISTRO DE MADUREZ DEL SISTEMA\n\n-   **Versión del sistema:** 5.7.24\n-   **Fecha:** 2026-03-06\n-   **Score global:** 9.45\n-   **Top 3 Avances:**\n    1.  **Welcome Landing**: Transformación del acceso al sistema en una herramienta comercial.\n    2.  **Bento Grid UI**: Layout moderno para la presentación de módulos.\n    3.  **Automation Narratives**: Visualización efectiva del ahorro de tiempo mediante diagramas SVG.\n\n---\n\n",
  "metadata": {
    "source": "knowledge/docs/reference/AUDIT_LOG.md",
    "header": "5. REGISTRO DE MADUREZ DEL SISTEMA"
  }
}