{
  "id": "components_src_components_views_terminal_views_inventory_InventoryAdjustmentModal_tsx",
  "content": "{\"business_logic\": \"L\\u00f3gica de negocio para InventoryAdjustmentModal.\", \"dependencies\": [\"react\", \"lucide-react\", \"@/types\", \"@/lib/inventory-logic\", \"@/lib/utils\", \"sonner\", \"@/hooks/ui/useMobile\"], \"domain\": \"UI\", \"exports\": [], \"id\": \"src/components/views/terminal/views/inventory/InventoryAdjustmentModal.tsx\", \"name\": \"InventoryAdjustmentModal.tsx\", \"technical_description\": \"M\\u00f3dulo t\\u00e9cnico InventoryAdjustmentModal.\", \"user_description\": \"Elemento de la interfaz de usuario para interactuar con InventoryAdjustmentModal.tsx.\"}",
  "metadata": {
    "source": "knowledge/components.json",
    "index": 76,
    "domain": "components"
  }
}